MANIFEST.in
README.rst
setup.py
preprocessor/__init__.py
preprocessor/api.py
preprocessor/constants.py
preprocessor/parse.py
preprocessor/preprocess.py
preprocessor/utils.py
requirements/dev-requirements.txt
requirements/requirements.txt
tests/__init__.py
tests/test_api.py
tweet_preprocessor.egg-info/PKG-INFO
tweet_preprocessor.egg-info/SOURCES.txt
tweet_preprocessor.egg-info/dependency_links.txt
tweet_preprocessor.egg-info/top_level.txt