Metadata-Version: 1.1
Name: tweet-preprocessor
Version: 0.2.0
Summary: Elegant tweet preprocessing
Home-page: https://github.com/s/preprocessor
Author: Said Özcan
Author-email: saidozcn@gmail.com
License: UNKNOWN
Keywords: machine learning,preprocessing,tweet
Platform: UNKNOWN
Classifier: Development Status :: 5 - Production/Stable
Classifier: Environment :: Console
Classifier: Intended Audience :: Developers
Classifier: License :: OSI Approved :: BSD License
Classifier: Operating System :: OS Independent
Classifier: Programming Language :: Python
Classifier: Programming Language :: Python :: 3
Classifier: Programming Language :: Python :: 3.4
Classifier: Programming Language :: Python :: 3.5
Classifier: Programming Language :: Python :: Implementation
Classifier: Programming Language :: Python :: Implementation :: CPython
Classifier: Programming Language :: Python :: Implementation :: PyPy
